htsprophet/__init__.py
htsprophet/fitForecast.py
htsprophet/hts.py
htsprophet/htsPlot.py
htsprophet/makeWeekly.py
htsprophet/orderHier.py
htsprophet/runHTS.py
htsprophet-0.1.0.dist-info/DESCRIPTION.rst
htsprophet-0.1.0.dist-info/METADATA
htsprophet-0.1.0.dist-info/RECORD
htsprophet-0.1.0.dist-info/WHEEL
htsprophet-0.1.0.dist-info/metadata.json
htsprophet-0.1.0.dist-info/top_level.txt
