Metadata-Version: 2.0
Name: htsprophet
Version: 0.1.0
Summary: Creates Hierarchical Time Series Forecasts with Facebook's Prophet tool
Home-page: https://github.com/CollinRooney12/htsprophet
Author: Collin Rooney
Author-email: CollinRooney12@gmail.com
License: MIT
Keywords: hts time series hierarchy forecast Prophet
Platform: UNKNOWN
Requires-Dist: fbprophet
Requires-Dist: matplotlib
Requires-Dist: numpy
Requires-Dist: pandas (>=0.18.1)
Requires-Dist: scikit-learn (>=0.18)
